mjm/__init__.py
mjm/tool.py
mjm/conf/__init__.py
mjm/conf/param.py
mjm/graph_test/__init__.py
mjm/graph_test/graph_python_connector.py
mjm/graph_test/write_graph_data.py
mjm/learning/__init__.py
mjm/learning/abi_api_backup.py
mjm/learning/create_hash.py
mjm/learning/flink_finder测试.py
mjm/learning/loudou.py
mjm/learning/loudou2.py
mjm/learning/parse_url.py
mjm/learning/python_flask.py
mjm/learning/test1.py
mjm/learning/zhiliang.py
mjm/learning/飞书.py
mjm/learning/jiuzhang_learning/__init__.py
mjm/learning/jiuzhang_learning/api.py
mjm/learning/jiuzhang_learning/tool.py
mjm/learning/pyspark_learning/1.read_odps.py
mjm/learning/pyspark_learning/2.read_odps2.py
mjm/learning/pyspark_learning/3.read_odps3.py
mjm/learning/pyspark_learning/4.write_hudi_spark2.4.py
mjm/learning/pyspark_learning/5.write_hudi_spark3.1.1.py
mjm/learning/pyspark_learning/6.read_hudi_spark.py
mjm/learning/pyspark_learning/7.read_lebo_spark.py
mjm/learning/pyspark_learning/__init__.py
mjm/learning/pyspark_learning/read_localFile_windows.py
mjm/learning/re/__init__.py
mjm/learning/re/re_split_test2.py
mjm/learning/re/re_sub_test1.py
mjm/learning/yaml2json/__init__.py
mjm/learning/yaml2json/yaml2json.py
mjm/lebo_utils/__init__.py
mjm/lebo_utils/abi/__init__.py
mjm/lebo_utils/abi/abi_api.py
mjm/lebo_utils/abi/abi_api2.py
mjm/lebo_utils/auto_sql/__init__.py
mjm/lebo_utils/auto_sql/usage.py
mjm/lebo_utils/hologres/__init__.py
mjm/lebo_utils/hologres/auto_run_app_version_group.py
mjm/lebo_utils/hologres/update_app_version.py
mjm/lebo_utils/hologres/update_ods_ad_3rd_tag_package_detail.py
mjm/lebo_utils/jiuzhang/__init__.py
mjm/lebo_utils/jiuzhang/api.py
mjm/lebo_utils/jiuzhang/api_test.py
mjm/lebo_utils/lebo_flink/__init__.py
mjm/lebo_utils/lebo_flink/f_coldOss2mc.py
mjm/lebo_utils/lebo_flink/read_cold_storage.py
mjm/lebo_utils/mc/1.py
mjm/lebo_utils/mc/__init__.py
mjm/lebo_utils/mc/auto_sql.py
mjm/lebo_utils/mc/clodOss2mc.py
mjm/lebo_utils/mc/clodOss2mc2.py
mjm/lebo_utils/mc/get_mc_meta.py
mjm-0.2.2.dist-info/METADATA
mjm-0.2.2.dist-info/WHEEL
mjm-0.2.2.dist-info/top_level.txt
mjm-0.2.2.dist-info/RECORD
